LICENSE
MANIFEST.in
README.rst
setup.py
basic_email/__init__.py
basic_email/models.py
basic_email/send.py
basic_email/urls.py
basic_email/views.py
django_basic_email.egg-info/PKG-INFO
django_basic_email.egg-info/SOURCES.txt
django_basic_email.egg-info/dependency_links.txt
django_basic_email.egg-info/not-zip-safe
django_basic_email.egg-info/top_level.txt
example_project/__init__.py
example_project/manage.py
example_project/settings.py
example_project/test_runner.py
example_project/urls.py
example_project/views.py
example_project/tests/__init__.py
example_project/tests/tests.py
requirements/external_apps.txt
requirements/test_apps.txt