Metadata-Version: 1.1
Name: django-basic-email
Version: 0.0.2
Summary: Django Basic Email application
Home-page: https://github.com/ArabellaTech/django-basic-email
Author: Arabella
Author-email: team@arabel.la
License: BSD
Download-URL: http://pypi.python.org/packages/source/d/django-basic-email/django-basic-email-0.0.2.tar.gz
Platform: UNKNOWN
Classifier: Development Status :: 5 - Production/Stable
Classifier: Environment :: Web Environment
Classifier: Intended Audience :: Developers
Classifier: License :: OSI Approved :: BSD License
Classifier: Operating System :: OS Independent
Classifier: Programming Language :: Python
Classifier: Framework :: Django
Classifier: Programming Language :: Python :: 2.6
Classifier: Programming Language :: Python :: 2.7
Classifier: Programming Language :: Python :: 3.3
Classifier: Programming Language :: Python :: 3.4
Classifier: Programming Language :: JavaScript
Classifier: Topic :: Internet :: WWW/HTTP :: Site Management
